pydeas/PydeasDB.py
pydeas/__init__.py
pydeas-1.0.2.dist-info/METADATA
pydeas-1.0.2.dist-info/WHEEL
pydeas-1.0.2.dist-info/top_level.txt
pydeas-1.0.2.dist-info/RECORD
