Metadata-Version: 2.1
Name: pydeas
Version: 1.0.2
Summary: A simple db package
Home-page: UNKNOWN
Author: Bilodev (Antonio Bilotta)
Author-email: bilotta.antonio.biz@gmail.com
License: UNKNOWN
Keywords: python,database,csv,relational database,relational,pydesDb,pydes
Platform: UNKNOWN
Classifier: Development Status :: 5 - Production/Stable
Classifier: Intended Audience :: Developers
Classifier: Programming Language :: Python :: 3
Classifier: Operating System :: Unix
Classifier: Operating System :: MacOS :: MacOS X
Classifier: Operating System :: Microsoft :: Windows
Requires-Dist: rich
Requires-Dist: pandas
